stdlb/__init__.py
stdlb/cached_property.py
stdlb-0.1.0.dist-info/METADATA
stdlb-0.1.0.dist-info/WHEEL
stdlb-0.1.0.dist-info/RECORD
