Metadata-Version: 2.4
Name: stdlb
Version: 0.1.0
Summary: Wildcard-import the Python standard library
Project-URL: Homepage, https://github.com/runsascoded/stdlb
Project-URL: Repository, https://github.com/runsascoded/stdlb
Project-URL: Issues, https://github.com/runsascoded/stdlb/issues
Author-email: Ryan Williams <ryan@runsascoded.com>
License: MIT
Classifier: Development Status :: 4 - Beta
Classifier: Intended Audience :: Developers
Classifier: License :: OSI Approved :: MIT License
Classifier: Programming Language :: Python :: 3
Classifier: Programming Language :: Python :: 3.10
Classifier: Programming Language :: Python :: 3.11
Classifier: Programming Language :: Python :: 3.12
Classifier: Programming Language :: Python :: 3.13
Requires-Python: >=3.10
